vsslite/__init__.py
vsslite/__main__.py
vsslite/chat.py
vsslite/chatgpt_processor.py
vsslite/client.py
vsslite/lcclient.py
vsslite/lcserver.py
vsslite/line.py
vsslite/server.py
vsslite/vsslite.py
vsslite-0.6.1.dist-info/LICENSE
vsslite-0.6.1.dist-info/METADATA
vsslite-0.6.1.dist-info/WHEEL
vsslite-0.6.1.dist-info/top_level.txt
vsslite-0.6.1.dist-info/RECORD
