Metadata-Version: 2.1
Name: vsslite
Version: 0.6.1
Summary: A vector similarity search engine for humans🥳
Home-page: https://github.com/uezo/vsslite
Author: uezo
Author-email: uezo@uezo.net
Maintainer: uezo
Maintainer-email: uezo@uezo.net
License: MIT
Classifier: Programming Language :: Python :: 3
License-File: LICENSE
Requires-Dist: openai ==0.28.1
Requires-Dist: fastapi ==0.103.2
Requires-Dist: uvicorn ==0.23.2
Requires-Dist: aiofiles ==23.2.1
Requires-Dist: langchain ==0.0.314
Requires-Dist: pdfminer.six ==20221105
Requires-Dist: chromadb ==0.4.14
Requires-Dist: tiktoken ==0.5.1
Requires-Dist: jq ==1.6.0
Requires-Dist: numpy ==1.26.0
Requires-Dist: sqlite-vss ==0.1.2
